v2ray_stats/__init__.py
v2ray_stats/__main__.py
v2ray_stats/collector.py
v2ray_stats/config.py
v2ray_stats/email.py
v2ray_stats/output.py
v2ray_stats/query.py
v2ray_stats/scheduler.py
v2ray_stats/utils.py
v2ray_stats/v2ctl.py
V2ray.Stats-0.3.2.dist-info/LICENSE
V2ray.Stats-0.3.2.dist-info/METADATA
V2ray.Stats-0.3.2.dist-info/WHEEL
V2ray.Stats-0.3.2.dist-info/top_level.txt
V2ray.Stats-0.3.2.dist-info/RECORD
